minesweeper/__init__.py
minesweeper/images/minesweeper-sprites.png
minesweeper/images/faces/2000.png
minesweeper/images/faces/monochrome.png
minesweeper/images/scores/2000.png
minesweeper/images/scores/monochrome.png
minesweeper/images/tiles/2.0.png
minesweeper/images/tiles/2.9.png
minesweeper/images/tiles/2000.png
minesweeper/images/tiles/95.png
minesweeper/images/tiles/fiorito-2000.png
minesweeper/images/tiles/fiorito-monochrome.png
minesweeper/images/tiles/fiorito-xp.png
minesweeper/images/tiles/monochrome.png
minesweeper/sprites/__init__.py
minesweeper/sprites/face.py
minesweeper/sprites/score.py
minesweeper/sprites/spritesheet.py
minesweeper/sprites/tile.py
pygame_minesweeper_sprites-1.0.41.dist-info/LICENSE
pygame_minesweeper_sprites-1.0.41.dist-info/METADATA
pygame_minesweeper_sprites-1.0.41.dist-info/WHEEL
pygame_minesweeper_sprites-1.0.41.dist-info/top_level.txt
pygame_minesweeper_sprites-1.0.41.dist-info/RECORD
