Metadata-Version: 2.1
Name: pygame-minesweeper-sprites
Version: 1.0.41
Summary: Minesweeper sprites for pygame applications
Home-page: https://github.com/andreasisnes/Elitekollektivet.Minesweeper.Sprites
Author: Andreas Isnes Nilsen
Author-email: andreas.isnes@gmail.com
License: UNKNOWN
Platform: UNKNOWN
Classifier: Programming Language :: Python :: 3
Classifier: License :: OSI Approved :: MIT License
Classifier: Operating System :: OS Independent
Requires-Dist: pygame
